pdfchat/__init__.py
pdfchat/main.py
pdfchat-0.1.1.dist-info/METADATA
pdfchat-0.1.1.dist-info/WHEEL
pdfchat-0.1.1.dist-info/entry_points.txt
pdfchat-0.1.1.dist-info/licenses/LICENSE
pdfchat-0.1.1.dist-info/RECORD
