Metadata-Version: 2.4
Name: pdfchat
Version: 0.1.1
Summary: CLI app to quickly chat with your PDFs locally
Author-email: Ibrahim Habib <ibrahimhabib.eg@gmail.com>
License-File: LICENSE
Requires-Python: >=3.10
Requires-Dist: llama-index-embeddings-huggingface>=0.5.3
Requires-Dist: llama-index-llms-ollama>=0.5.4
Requires-Dist: marker-pdf>=1.6.2
Requires-Dist: ollama>=0.4.7
Requires-Dist: pypdf2>=3.0.1
Requires-Dist: rich>=14.0.0
Requires-Dist: typer>=0.15.2
